no_vtf_desktop/__init__.py
no_vtf_desktop/__main__.py
no_vtf_desktop/_admin.py
no_vtf_desktop/_desktop.py
no_vtf_desktop/_lock.py
no_vtf_desktop/_metadata.py
no_vtf_desktop/_version.py
no_vtf_desktop/installation.py
no_vtf_desktop/main.py
no_vtf_desktop/py.typed
no_vtf_desktop/uninstall/__init__.py
no_vtf_desktop/uninstall/__main__.py
no_vtf_desktop-0.1.4.data/data/share/applications/no_vtf.desktop
no_vtf_desktop-0.1.4.data/data/share/icons/hicolor/128x128/mimetypes/no_vtf-application-x-vtf.png
no_vtf_desktop-0.1.4.data/data/share/icons/hicolor/16x16/mimetypes/no_vtf-application-x-vtf.png
no_vtf_desktop-0.1.4.data/data/share/icons/hicolor/22x22/mimetypes/no_vtf-application-x-vtf.png
no_vtf_desktop-0.1.4.data/data/share/icons/hicolor/24x24/mimetypes/no_vtf-application-x-vtf.png
no_vtf_desktop-0.1.4.data/data/share/icons/hicolor/256x256/mimetypes/no_vtf-application-x-vtf.png
no_vtf_desktop-0.1.4.data/data/share/icons/hicolor/32x32/mimetypes/no_vtf-application-x-vtf.png
no_vtf_desktop-0.1.4.data/data/share/icons/hicolor/48x48/mimetypes/no_vtf-application-x-vtf.png
no_vtf_desktop-0.1.4.data/data/share/icons/hicolor/64x64/mimetypes/no_vtf-application-x-vtf.png
no_vtf_desktop-0.1.4.data/data/share/icons/hicolor/scalable/mimetypes/no_vtf-application-x-vtf.svg
no_vtf_desktop-0.1.4.data/data/share/mime/packages/no_vtf.xml
no_vtf_desktop-0.1.4.data/data/share/polkit-1/actions/no-vtf-desktop.policy
no_vtf_desktop-0.1.4.data/data/share/thumbnailers/no_vtf.thumbnailer
no_vtf_desktop-0.1.4.dist-info/GPL-3.0-or-later.txt
no_vtf_desktop-0.1.4.dist-info/METADATA
no_vtf_desktop-0.1.4.dist-info/WHEEL
no_vtf_desktop-0.1.4.dist-info/entry_points.txt
no_vtf_desktop-0.1.4.dist-info/top_level.txt
no_vtf_desktop-0.1.4.dist-info/RECORD
