Metadata-Version: 2.1
Name: no_vtf-desktop
Version: 0.1.4
Summary: Desktop integration for no_vtf (Linux-only)
Home-page: https://git.sr.ht/~b5327157/no_vtf-desktop
Author: b5327157
Author-email: b5327157@protonmail.com
License: GPL-3.0-or-later
Project-URL: Changelog, https://git.sr.ht/~b5327157/no_vtf-desktop/refs
Project-URL: Mailing list, https://lists.sr.ht/~b5327157/no_vtf
Project-URL: Ticket tracker, https://todo.sr.ht/~b5327157/no_vtf
Project-URL: Wiki, https://developer.valvesoftware.com/wiki/no_vtf
Keywords: no_vtf,Source Engine,VTF,Valve Texture Format
Classifier: Development Status :: 4 - Beta
Classifier: Environment :: Plugins
Classifier: Intended Audience :: End Users/Desktop
Classifier: License :: OSI Approved :: GNU General Public License v3 or later (GPLv3+)
Classifier: Natural Language :: English
Classifier: Operating System :: POSIX :: Linux
Classifier: Programming Language :: Python :: 3
Classifier: Programming Language :: Python :: 3 :: Only
Classifier: Programming Language :: Python :: 3.10
Classifier: Programming Language :: Python :: 3.11
Classifier: Programming Language :: Python :: 3.12
Classifier: Programming Language :: Python :: 3.13
Classifier: Topic :: Multimedia :: Graphics :: Graphics Conversion
Classifier: Typing :: Typed
Requires-Python: >=3.10
License-File: LICENSES/GPL-3.0-or-later.txt
Requires-Dist: click<9,>=8.1.7
Requires-Dist: filelock<4,>=3.16.1
Requires-Dist: imageio<3,>=2.36.0
Requires-Dist: no_vtf<6,>=5.1.0
Requires-Dist: pip
Requires-Dist: pyxdg<1,>=0.28
